open_pydb/__init__.py
open_pydb-0.1.0.dist-info/LICENSE
open_pydb-0.1.0.dist-info/METADATA
open_pydb-0.1.0.dist-info/WHEEL
open_pydb-0.1.0.dist-info/top_level.txt
open_pydb-0.1.0.dist-info/RECORD
