Metadata-Version: 2.1
Name: open_pydb
Version: 0.1.0
Summary: Open_PyDb is a unique way to change open source unstructure dataabases, it makes use of Jsonl files to store big amounts of data
Author-email: John Paul Paredes <johnpar2004@gmail.com>
Project-URL: Homepage, https://github.com/JohnPaul0403/open-db
Classifier: Programming Language :: Python :: 3
Classifier: License :: OSI Approved :: MIT License
Classifier: Operating System :: OS Independent
Requires-Python: >=3.8
License-File: LICENSE
